app_logger.py
goose.py
goose_utils.py
goose_version.py
postgoose-0.1.1.dist-info/LICENSE
postgoose-0.1.1.dist-info/METADATA
postgoose-0.1.1.dist-info/WHEEL
postgoose-0.1.1.dist-info/entry_points.txt
postgoose-0.1.1.dist-info/top_level.txt
postgoose-0.1.1.dist-info/RECORD
