Metadata-Version: 2.1
Name: postgoose
Version: 0.1.1
Summary: SQL migrations for Postgres
Home-page: https://github.com/leantaas/postgoose
Author: dmb
Author-email: opensource@leantaas.com
License: Apache License 2.0
Platform: UNKNOWN
Classifier: License :: OSI Approved :: Apache Software License
Classifier: Programming Language :: Python
Classifier: Programming Language :: Python :: 3
Classifier: Programming Language :: Python :: 3.6
Classifier: Programming Language :: Python :: Implementation :: CPython
Requires-Python: >=3.6.0
License-File: LICENSE
Requires-Dist: psycopg2-binary (>=2.8.4)
